[
    {
        "name": "Ant",
        "source": "<a href=\"https:\/\/en.wikipedia.org\/wiki\/Ant\" target=\"_blank\"><img width=\"24\" height=\"24\" src=\"\/images\/poster\/edupack\/icon\/24-en-wiki.png\" \/><\/a>",
        "audio": "<audio src=\"https:\/\/www.w3schools.com\/html\/horse.mp3\" class=\"audioplay en\"><\/audio>",
        "name_jp": "\u30a2\u30ea",
        "source_jp": "<a href=\"https:\/\/ja.wikipedia.org\/wiki\/%E3%82%A2%E3%83%AA\" target=\"_blank\"><img width=\"24\" height=\"24\" src=\"\/images\/poster\/edupack\/icon\/24-jp-wiki.png\" \/><\/a>",
        "audio_jp": "<audio src=\"https:\/\/www.w3schools.com\/html\/horse.mp3\" class=\"audioplay jp\"><\/audio>",
        "name_de": "Ameise (f)",
        "source_de": "<a href=\"https:\/\/de.wikipedia.org\/wiki\/Ameisen\" target=\"_blank\"><img width=\"24\" height=\"24\" src=\"\/images\/poster\/edupack\/icon\/24-en-wiki.png\" \/><\/a>",
        "audio_de": "<audio src=\"https:\/\/www.w3schools.com\/html\/horse.mp3\" class=\"audioplay jp\"><\/audio>",
        "id": 1
    },
    {
        "name": "Bear",
        "source": "<a href=\"https:\/\/en.wikipedia.org\/wiki\/Bear\" target=\"_blank\"><img width=\"24\" height=\"24\" src=\"\/images\/poster\/edupack\/icon\/24-en-wiki.png\" \/><\/a>",
        "audio": "<audio src=\"https:\/\/www.w3schools.com\/html\/horse.mp3\" class=\"audioplay en\"><\/audio>",
        "name_jp": "\u30af\u30de",
        "source_jp": "<a href=\"https:\/\/ja.wikipedia.org\/wiki\/%E3%82%AF%E3%83%9E\" target=\"_blank\"><img width=\"24\" height=\"24\" src=\"\/images\/poster\/edupack\/icon\/24-jp-wiki.png\" \/><\/a>",
        "audio_jp": "<audio src=\"https:\/\/www.w3schools.com\/html\/horse.mp3\" class=\"audioplay jp\"><\/audio>",
        "name_de": "B\u00e4r (m) or, B\u00e4ren",
        "source_de": "<a href=\"https:\/\/de.wikipedia.org\/wiki\/B%C3%A4ren\" target=\"_blank\"><img width=\"24\" height=\"24\" src=\"\/images\/poster\/edupack\/icon\/24-en-wiki.png\" \/><\/a>",
        "audio_de": "<audio src=\"https:\/\/www.w3schools.com\/html\/horse.mp3\" class=\"audioplay jp\"><\/audio>",
        "id": 2
    },
    {
        "name": "Chipmunk",
        "source": "<a href=\"https:\/\/en.wikipedia.org\/wiki\/Chipmunk\" target=\"_blank\"><img width=\"24\" height=\"24\" src=\"\/images\/poster\/edupack\/icon\/24-en-wiki.png\" \/><\/a>",
        "audio": "<audio src=\"https:\/\/www.w3schools.com\/html\/horse.mp3\" class=\"audioplay en\"><\/audio>",
        "name_jp": "\u30b7\u30de\u30ea\u30b9",
        "source_jp": "<a href=\"https:\/\/ja.wikipedia.org\/wiki\/%E3%82%B7%E3%83%9E%E3%83%AA%E3%82%B9\" target=\"_blank\"><img width=\"24\" height=\"24\" src=\"\/images\/poster\/edupack\/icon\/24-jp-wiki.png\" \/><\/a>",
        "audio_jp": "<audio src=\"https:\/\/www.w3schools.com\/html\/horse.mp3\" class=\"audioplay jp\"><\/audio>",
        "name_de": "Chipmunk (m)",
        "source_de": "<a href=\"https:\/\/de.wikipedia.org\/wiki\/Streifenh%C3%B6rnchen\" target=\"_blank\"><img width=\"24\" height=\"24\" src=\"\/images\/poster\/edupack\/icon\/24-en-wiki.png\" \/><\/a>",
        "audio_de": "<audio src=\"https:\/\/www.w3schools.com\/html\/horse.mp3\" class=\"audioplay jp\"><\/audio>",
        "id": 3
    },
    {
        "name": "Dolphin",
        "source": "<a href=\"https:\/\/en.wikipedia.org\/wiki\/Dolphin\" target=\"_blank\"><img width=\"24\" height=\"24\" src=\"\/images\/poster\/edupack\/icon\/24-en-wiki.png\" \/><\/a>",
        "audio": "<audio src=\"https:\/\/www.w3schools.com\/html\/horse.mp3\" class=\"audioplay en\"><\/audio>",
        "name_jp": "\u30a4\u30eb\u30ab",
        "source_jp": "<a href=\"https:\/\/ja.wikipedia.org\/wiki\/%E3%82%A4%E3%83%AB%E3%82%AB\" target=\"_blank\"><img width=\"24\" height=\"24\" src=\"\/images\/poster\/edupack\/icon\/24-jp-wiki.png\" \/><\/a>",
        "audio_jp": "<audio src=\"https:\/\/www.w3schools.com\/html\/horse.mp3\" class=\"audioplay jp\"><\/audio>",
        "name_de": "Delfine (m)",
        "source_de": "<a href=\"https:\/\/de.wikipedia.org\/wiki\/Delfine\" target=\"_blank\"><img width=\"24\" height=\"24\" src=\"\/images\/poster\/edupack\/icon\/24-en-wiki.png\" \/><\/a>",
        "audio_de": "<audio src=\"https:\/\/www.w3schools.com\/html\/horse.mp3\" class=\"audioplay jp\"><\/audio>",
        "id": 4
    },
    {
        "name": "Elephant",
        "source": "<a href=\"https:\/\/en.wikipedia.org\/wiki\/Elephant\" target=\"_blank\"><img width=\"24\" height=\"24\" src=\"\/images\/poster\/edupack\/icon\/24-en-wiki.png\" \/><\/a>",
        "audio": "<audio src=\"https:\/\/www.w3schools.com\/html\/horse.mp3\" class=\"audioplay en\"><\/audio>",
        "name_jp": "\u30be\u30a6",
        "source_jp": "<a href=\"https:\/\/ja.wikipedia.org\/wiki\/%E3%82%BE%E3%82%A6\" target=\"_blank\"><img width=\"24\" height=\"24\" src=\"\/images\/poster\/edupack\/icon\/24-jp-wiki.png\" \/><\/a>",
        "audio_jp": "<audio src=\"https:\/\/www.w3schools.com\/html\/horse.mp3\" class=\"audioplay jp\"><\/audio>",
        "name_de": "Elefanten (m)",
        "source_de": "<a href=\"https:\/\/de.wikipedia.org\/wiki\/Elefanten\" target=\"_blank\"><img width=\"24\" height=\"24\" src=\"\/images\/poster\/edupack\/icon\/24-en-wiki.png\" \/><\/a>",
        "audio_de": "<audio src=\"https:\/\/www.w3schools.com\/html\/horse.mp3\" class=\"audioplay jp\"><\/audio>",
        "id": 5
    },
    {
        "name": "Fox",
        "source": "<a href=\"https:\/\/en.wikipedia.org\/wiki\/Fox\" target=\"_blank\"><img width=\"24\" height=\"24\" src=\"\/images\/poster\/edupack\/icon\/24-en-wiki.png\" \/><\/a>",
        "audio": "<audio src=\"https:\/\/www.w3schools.com\/html\/horse.mp3\" class=\"audioplay en\"><\/audio>",
        "name_jp": "\u30ad\u30c4\u30cd",
        "source_jp": "<a href=\"https:\/\/ja.wikipedia.org\/wiki\/%E3%82%AD%E3%83%84%E3%83%8D\" target=\"_blank\"><img width=\"24\" height=\"24\" src=\"\/images\/poster\/edupack\/icon\/24-jp-wiki.png\" \/><\/a>",
        "audio_jp": "<audio src=\"https:\/\/www.w3schools.com\/html\/horse.mp3\" class=\"audioplay jp\"><\/audio>",
        "name_de": "Fuchs (m)",
        "source_de": "<a href=\"https:\/\/de.wikipedia.org\/wiki\/Fuchs_(Raubtier)\" target=\"_blank\"><img width=\"24\" height=\"24\" src=\"\/images\/poster\/edupack\/icon\/24-en-wiki.png\" \/><\/a>",
        "audio_de": "<audio src=\"https:\/\/www.w3schools.com\/html\/horse.mp3\" class=\"audioplay jp\"><\/audio>",
        "id": 6
    },
    {
        "name": "Giraffe",
        "source": "<a href=\"https:\/\/en.wikipedia.org\/wiki\/Giraffe\" target=\"_blank\"><img width=\"24\" height=\"24\" src=\"\/images\/poster\/edupack\/icon\/24-en-wiki.png\" \/><\/a>",
        "audio": "<audio src=\"https:\/\/www.w3schools.com\/html\/horse.mp3\" class=\"audioplay en\"><\/audio>",
        "name_jp": "\u30ad\u30ea\u30f3",
        "source_jp": "<a href=\"https:\/\/ja.wikipedia.org\/wiki\/%E3%82%AD%E3%83%AA%E3%83%B3\" target=\"_blank\"><img width=\"24\" height=\"24\" src=\"\/images\/poster\/edupack\/icon\/24-jp-wiki.png\" \/><\/a>",
        "audio_jp": "<audio src=\"https:\/\/www.w3schools.com\/html\/horse.mp3\" class=\"audioplay jp\"><\/audio>",
        "name_de": "Giraffe (f)",
        "source_de": "<a href=\"https:\/\/de.wikipedia.org\/wiki\/Giraffen\" target=\"_blank\"><img width=\"24\" height=\"24\" src=\"\/images\/poster\/edupack\/icon\/24-en-wiki.png\" \/><\/a>",
        "audio_de": "<audio src=\"https:\/\/www.w3schools.com\/html\/horse.mp3\" class=\"audioplay jp\"><\/audio>",
        "id": 7
    },
    {
        "name": "Hamster",
        "source": "<a href=\"https:\/\/en.wikipedia.org\/wiki\/Hamster\" target=\"_blank\"><img width=\"24\" height=\"24\" src=\"\/images\/poster\/edupack\/icon\/24-en-wiki.png\" \/><\/a>",
        "audio": "<audio src=\"https:\/\/www.w3schools.com\/html\/horse.mp3\" class=\"audioplay en\"><\/audio>",
        "name_jp": "\u30cf\u30e0\u30b9\u30bf\u30fc",
        "source_jp": "<a href=\"https:\/\/ja.wikipedia.org\/wiki\/%E3%83%8F%E3%83%A0%E3%82%B9%E3%82%BF%E3%83%BC\" target=\"_blank\"><img width=\"24\" height=\"24\" src=\"\/images\/poster\/edupack\/icon\/24-jp-wiki.png\" \/><\/a>",
        "audio_jp": "<audio src=\"https:\/\/www.w3schools.com\/html\/horse.mp3\" class=\"audioplay jp\"><\/audio>",
        "name_de": "Hamster (m)",
        "source_de": "<a href=\"https:\/\/de.wikipedia.org\/wiki\/Hamster\" target=\"_blank\"><img width=\"24\" height=\"24\" src=\"\/images\/poster\/edupack\/icon\/24-en-wiki.png\" \/><\/a>",
        "audio_de": "<audio src=\"https:\/\/www.w3schools.com\/html\/horse.mp3\" class=\"audioplay jp\"><\/audio>",
        "id": 8
    },
    {
        "name": "Ibis",
        "source": "<a href=\"https:\/\/en.wikipedia.org\/wiki\/Ibis\" target=\"_blank\"><img width=\"24\" height=\"24\" src=\"\/images\/poster\/edupack\/icon\/24-en-wiki.png\" \/><\/a>",
        "audio": "<audio src=\"https:\/\/www.w3schools.com\/html\/horse.mp3\" class=\"audioplay en\"><\/audio>",
        "name_jp": "\u30c8\u30ad",
        "source_jp": "<a href=\"https:\/\/ja.wikipedia.org\/wiki\/%E3%83%88%E3%82%AD\" target=\"_blank\"><img width=\"24\" height=\"24\" src=\"\/images\/poster\/edupack\/icon\/24-jp-wiki.png\" \/><\/a>",
        "audio_jp": "<audio src=\"https:\/\/www.w3schools.com\/html\/horse.mp3\" class=\"audioplay jp\"><\/audio>",
        "name_de": "Ibis (m)",
        "source_de": "<a href=\"https:\/\/de.wikipedia.org\/wiki\/Heiliger_Ibis\" target=\"_blank\"><img width=\"24\" height=\"24\" src=\"\/images\/poster\/edupack\/icon\/24-en-wiki.png\" \/><\/a>",
        "audio_de": "<audio src=\"https:\/\/www.w3schools.com\/html\/horse.mp3\" class=\"audioplay jp\"><\/audio>",
        "id": 9
    },
    {
        "name": "Jaguar",
        "source": "<a href=\"https:\/\/en.wikipedia.org\/wiki\/Jaguar\" target=\"_blank\"><img width=\"24\" height=\"24\" src=\"\/images\/poster\/edupack\/icon\/24-en-wiki.png\" \/><\/a>",
        "audio": "<audio src=\"https:\/\/www.w3schools.com\/html\/horse.mp3\" class=\"audioplay en\"><\/audio>",
        "name_jp": "\u30b8\u30e3\u30ac\u30fc",
        "source_jp": "<a href=\"https:\/\/ja.wikipedia.org\/wiki\/%E3%82%B8%E3%83%A3%E3%82%AC%E3%83%BC\" target=\"_blank\"><img width=\"24\" height=\"24\" src=\"\/images\/poster\/edupack\/icon\/24-jp-wiki.png\" \/><\/a>",
        "audio_jp": "<audio src=\"https:\/\/www.w3schools.com\/html\/horse.mp3\" class=\"audioplay jp\"><\/audio>",
        "name_de": "Jaguar (m)",
        "source_de": "<a href=\"https:\/\/de.wikipedia.org\/wiki\/Jaguar\" target=\"_blank\"><img width=\"24\" height=\"24\" src=\"\/images\/poster\/edupack\/icon\/24-en-wiki.png\" \/><\/a>",
        "audio_de": "<audio src=\"https:\/\/www.w3schools.com\/html\/horse.mp3\" class=\"audioplay jp\"><\/audio>",
        "id": 10
    },
    {
        "name": "Kangaroo",
        "source": "<a href=\"https:\/\/en.wikipedia.org\/wiki\/Kangaroo\" target=\"_blank\"><img width=\"24\" height=\"24\" src=\"\/images\/poster\/edupack\/icon\/24-en-wiki.png\" \/><\/a>",
        "audio": "<audio src=\"https:\/\/www.w3schools.com\/html\/horse.mp3\" class=\"audioplay en\"><\/audio>",
        "name_jp": "\u30ab\u30f3\u30ac\u30eb\u30fc",
        "source_jp": "<a href=\"https:\/\/ja.wikipedia.org\/wiki\/%E3%82%AB%E3%83%B3%E3%82%AC%E3%83%AB%E3%83%BC\" target=\"_blank\"><img width=\"24\" height=\"24\" src=\"\/images\/poster\/edupack\/icon\/24-jp-wiki.png\" \/><\/a>",
        "audio_jp": "<audio src=\"https:\/\/www.w3schools.com\/html\/horse.mp3\" class=\"audioplay jp\"><\/audio>",
        "name_de": "K\u00e4nguru (n)",
        "source_de": "<a href=\"https:\/\/de.wikipedia.org\/wiki\/K%C3%A4ngurus\" target=\"_blank\"><img width=\"24\" height=\"24\" src=\"\/images\/poster\/edupack\/icon\/24-en-wiki.png\" \/><\/a>",
        "audio_de": "<audio src=\"https:\/\/www.w3schools.com\/html\/horse.mp3\" class=\"audioplay jp\"><\/audio>",
        "id": 11
    },
    {
        "name": "Lion",
        "source": "<a href=\"https:\/\/en.wikipedia.org\/wiki\/Lion\" target=\"_blank\"><img width=\"24\" height=\"24\" src=\"\/images\/poster\/edupack\/icon\/24-en-wiki.png\" \/><\/a>",
        "audio": "<audio src=\"https:\/\/www.w3schools.com\/html\/horse.mp3\" class=\"audioplay en\"><\/audio>",
        "name_jp": "\u30e9\u30a4\u30aa\u30f3",
        "source_jp": "<a href=\"https:\/\/ja.wikipedia.org\/wiki\/%E3%83%A9%E3%82%A4%E3%82%AA%E3%83%B3\" target=\"_blank\"><img width=\"24\" height=\"24\" src=\"\/images\/poster\/edupack\/icon\/24-jp-wiki.png\" \/><\/a>",
        "audio_jp": "<audio src=\"https:\/\/www.w3schools.com\/html\/horse.mp3\" class=\"audioplay jp\"><\/audio>",
        "name_de": "L\u00f6we (m)",
        "source_de": "<a href=\"https:\/\/de.wikipedia.org\/wiki\/L%C3%B6we\" target=\"_blank\"><img width=\"24\" height=\"24\" src=\"\/images\/poster\/edupack\/icon\/24-en-wiki.png\" \/><\/a>",
        "audio_de": "<audio src=\"https:\/\/www.w3schools.com\/html\/horse.mp3\" class=\"audioplay jp\"><\/audio>",
        "id": 12
    },
    {
        "name": "Mouse",
        "source": "<a href=\"https:\/\/en.wikipedia.org\/wiki\/Mouse\" target=\"_blank\"><img width=\"24\" height=\"24\" src=\"\/images\/poster\/edupack\/icon\/24-en-wiki.png\" \/><\/a>",
        "audio": "<audio src=\"https:\/\/www.w3schools.com\/html\/horse.mp3\" class=\"audioplay en\"><\/audio>",
        "name_jp": "\u30de\u30a6\u30b9",
        "source_jp": "<a href=\"https:\/\/ja.wikipedia.org\/wiki\/%E3%83%8F%E3%83%84%E3%82%AB%E3%83%8D%E3%82%BA%E3%83%9F%E5%B1%9E\" target=\"_blank\"><img width=\"24\" height=\"24\" src=\"\/images\/poster\/edupack\/icon\/24-jp-wiki.png\" \/><\/a>",
        "audio_jp": "<audio src=\"https:\/\/www.w3schools.com\/html\/horse.mp3\" class=\"audioplay jp\"><\/audio>",
        "name_de": "M\u00e4use (f)",
        "source_de": "<a href=\"https:\/\/de.wikipedia.org\/wiki\/M%C3%A4use\" target=\"_blank\"><img width=\"24\" height=\"24\" src=\"\/images\/poster\/edupack\/icon\/24-en-wiki.png\" \/><\/a>",
        "audio_de": "<audio src=\"https:\/\/www.w3schools.com\/html\/horse.mp3\" class=\"audioplay jp\"><\/audio>",
        "id": 13
    },
    {
        "name": "Numbat",
        "source": "<a href=\"https:\/\/en.wikipedia.org\/wiki\/Numbat\" target=\"_blank\"><img width=\"24\" height=\"24\" src=\"\/images\/poster\/edupack\/icon\/24-en-wiki.png\" \/><\/a>",
        "audio": "<audio src=\"https:\/\/www.w3schools.com\/html\/horse.mp3\" class=\"audioplay en\"><\/audio>",
        "name_jp": "\u30d5\u30af\u30ed\u30a2\u30ea\u30af\u30a4",
        "source_jp": "<a href=\"https:\/\/ja.wikipedia.org\/wiki\/%E3%83%95%E3%82%AF%E3%83%AD%E3%82%A2%E3%83%AA%E3%82%AF%E3%82%A4\" target=\"_blank\"><img width=\"24\" height=\"24\" src=\"\/images\/poster\/edupack\/icon\/24-jp-wiki.png\" \/><\/a>",
        "audio_jp": "<audio src=\"https:\/\/www.w3schools.com\/html\/horse.mp3\" class=\"audioplay jp\"><\/audio>",
        "name_de": "Numbat (m)",
        "source_de": "<a href=\"https:\/\/de.wikipedia.org\/wiki\/Numbat\" target=\"_blank\"><img width=\"24\" height=\"24\" src=\"\/images\/poster\/edupack\/icon\/24-en-wiki.png\" \/><\/a>",
        "audio_de": "<audio src=\"https:\/\/www.w3schools.com\/html\/horse.mp3\" class=\"audioplay jp\"><\/audio>",
        "id": 14
    },
    {
        "name": "Otter",
        "source": "<a href=\"https:\/\/en.wikipedia.org\/wiki\/Otter\" target=\"_blank\"><img width=\"24\" height=\"24\" src=\"\/images\/poster\/edupack\/icon\/24-en-wiki.png\" \/><\/a>",
        "audio": "<audio src=\"https:\/\/www.w3schools.com\/html\/horse.mp3\" class=\"audioplay en\"><\/audio>",
        "name_jp": "\u30ab\u30ef\u30a6\u30bd",
        "source_jp": "<a href=\"https:\/\/ja.wikipedia.org\/wiki\/%E3%82%AB%E3%83%AF%E3%82%A6%E3%82%BD\" target=\"_blank\"><img width=\"24\" height=\"24\" src=\"\/images\/poster\/edupack\/icon\/24-jp-wiki.png\" \/><\/a>",
        "audio_jp": "<audio src=\"https:\/\/www.w3schools.com\/html\/horse.mp3\" class=\"audioplay jp\"><\/audio>",
        "name_de": "Otter (m)",
        "source_de": "<a href=\"https:\/\/de.wikipedia.org\/wiki\/Otter\" target=\"_blank\"><img width=\"24\" height=\"24\" src=\"\/images\/poster\/edupack\/icon\/24-en-wiki.png\" \/><\/a>",
        "audio_de": "<audio src=\"https:\/\/www.w3schools.com\/html\/horse.mp3\" class=\"audioplay jp\"><\/audio>",
        "id": 15
    },
    {
        "name": "Panda",
        "source": "<a href=\"https:\/\/en.wikipedia.org\/wiki\/Giant_panda\" target=\"_blank\"><img width=\"24\" height=\"24\" src=\"\/images\/poster\/edupack\/icon\/24-en-wiki.png\" \/><\/a>",
        "audio": "<audio src=\"https:\/\/www.w3schools.com\/html\/horse.mp3\" class=\"audioplay en\"><\/audio>",
        "name_jp": "\u30b8\u30e3\u30a4\u30a2\u30f3\u30c8\u30d1\u30f3\u30c0",
        "source_jp": "<a href=\"https:\/\/ja.wikipedia.org\/wiki\/%E3%82%B8%E3%83%A3%E3%82%A4%E3%82%A2%E3%83%B3%E3%83%88%E3%83%91%E3%83%B3%E3%83%80\" target=\"_blank\"><img width=\"24\" height=\"24\" src=\"\/images\/poster\/edupack\/icon\/24-jp-wiki.png\" \/><\/a>",
        "audio_jp": "<audio src=\"https:\/\/www.w3schools.com\/html\/horse.mp3\" class=\"audioplay jp\"><\/audio>",
        "name_de": "Pandab\u00e4r (m)",
        "source_de": "<a href=\"https:\/\/de.wikipedia.org\/wiki\/Gro%C3%9Fer_Panda\" target=\"_blank\"><img width=\"24\" height=\"24\" src=\"\/images\/poster\/edupack\/icon\/24-en-wiki.png\" \/><\/a>",
        "audio_de": "<audio src=\"https:\/\/www.w3schools.com\/html\/horse.mp3\" class=\"audioplay jp\"><\/audio>",
        "id": 16
    },
    {
        "name": "Quokka",
        "source": "<a href=\"https:\/\/en.wikipedia.org\/wiki\/Quokka\" target=\"_blank\"><img width=\"24\" height=\"24\" src=\"\/images\/poster\/edupack\/icon\/24-en-wiki.png\" \/><\/a>",
        "audio": "<audio src=\"https:\/\/www.w3schools.com\/html\/horse.mp3\" class=\"audioplay en\"><\/audio>",
        "name_jp": "\u30af\u30a2\u30c3\u30ab\u30ef\u30e9\u30d3\u30fc",
        "source_jp": "<a href=\"https:\/\/ja.wikipedia.org\/wiki\/%E3%82%AF%E3%82%A2%E3%83%83%E3%82%AB%E3%83%AF%E3%83%A9%E3%83%93%E3%83%BC\" target=\"_blank\"><img width=\"24\" height=\"24\" src=\"\/images\/poster\/edupack\/icon\/24-jp-wiki.png\" \/><\/a>",
        "audio_jp": "<audio src=\"https:\/\/www.w3schools.com\/html\/horse.mp3\" class=\"audioplay jp\"><\/audio>",
        "name_de": "Quokka (n)",
        "source_de": "<a href=\"https:\/\/de.wikipedia.org\/wiki\/Quokka\" target=\"_blank\"><img width=\"24\" height=\"24\" src=\"\/images\/poster\/edupack\/icon\/24-en-wiki.png\" \/><\/a>",
        "audio_de": "<audio src=\"https:\/\/www.w3schools.com\/html\/horse.mp3\" class=\"audioplay jp\"><\/audio>",
        "id": 17
    },
    {
        "name": "Robin",
        "source": "<a href=\"https:\/\/en.wikipedia.org\/wiki\/European_robin\" target=\"_blank\"><img width=\"24\" height=\"24\" src=\"\/images\/poster\/edupack\/icon\/24-en-wiki.png\" \/><\/a>",
        "audio": "<audio src=\"https:\/\/www.w3schools.com\/html\/horse.mp3\" class=\"audioplay en\"><\/audio>",
        "name_jp": "\u30b3\u30de\u30c9\u30ea",
        "source_jp": "<a href=\"https:\/\/ja.wikipedia.org\/wiki\/%E3%82%B3%E3%83%9E%E3%83%89%E3%83%AA\" target=\"_blank\"><img width=\"24\" height=\"24\" src=\"\/images\/poster\/edupack\/icon\/24-jp-wiki.png\" \/><\/a>",
        "audio_jp": "<audio src=\"https:\/\/www.w3schools.com\/html\/horse.mp3\" class=\"audioplay jp\"><\/audio>",
        "name_de": "Rotkehlchen (n)",
        "source_de": "<a href=\"https:\/\/de.wikipedia.org\/wiki\/Rotkehlchen\" target=\"_blank\"><img width=\"24\" height=\"24\" src=\"\/images\/poster\/edupack\/icon\/24-en-wiki.png\" \/><\/a>",
        "audio_de": "<audio src=\"https:\/\/www.w3schools.com\/html\/horse.mp3\" class=\"audioplay jp\"><\/audio>",
        "id": 18
    },
    {
        "name": "Stork",
        "source": "<a href=\"https:\/\/en.wikipedia.org\/wiki\/Stork\" target=\"_blank\"><img width=\"24\" height=\"24\" src=\"\/images\/poster\/edupack\/icon\/24-en-wiki.png\" \/><\/a>",
        "audio": "<audio src=\"https:\/\/www.w3schools.com\/html\/horse.mp3\" class=\"audioplay en\"><\/audio>",
        "name_jp": "\u30b3\u30a6\u30ce\u30c8\u30ea",
        "source_jp": "<a href=\"https:\/\/ja.wikipedia.org\/wiki\/%E3%82%B3%E3%82%A6%E3%83%8E%E3%83%88%E3%83%AA\" target=\"_blank\"><img width=\"24\" height=\"24\" src=\"\/images\/poster\/edupack\/icon\/24-jp-wiki.png\" \/><\/a>",
        "audio_jp": "<audio src=\"https:\/\/www.w3schools.com\/html\/horse.mp3\" class=\"audioplay jp\"><\/audio>",
        "name_de": "St\u00f6rche (m)",
        "source_de": "<a href=\"https:\/\/de.wikipedia.org\/wiki\/St%C3%B6rche\" target=\"_blank\"><img width=\"24\" height=\"24\" src=\"\/images\/poster\/edupack\/icon\/24-en-wiki.png\" \/><\/a>",
        "audio_de": "<audio src=\"https:\/\/www.w3schools.com\/html\/horse.mp3\" class=\"audioplay jp\"><\/audio>",
        "id": 19
    },
    {
        "name": "Tiger",
        "source": "<a href=\"https:\/\/en.wikipedia.org\/wiki\/Tiger\" target=\"_blank\"><img width=\"24\" height=\"24\" src=\"\/images\/poster\/edupack\/icon\/24-en-wiki.png\" \/><\/a>",
        "audio": "<audio src=\"https:\/\/www.w3schools.com\/html\/horse.mp3\" class=\"audioplay en\"><\/audio>",
        "name_jp": "\u30c8\u30e9",
        "source_jp": "<a href=\"https:\/\/ja.wikipedia.org\/wiki\/%E3%83%88%E3%83%A9\" target=\"_blank\"><img width=\"24\" height=\"24\" src=\"\/images\/poster\/edupack\/icon\/24-jp-wiki.png\" \/><\/a>",
        "audio_jp": "<audio src=\"https:\/\/www.w3schools.com\/html\/horse.mp3\" class=\"audioplay jp\"><\/audio>",
        "name_de": "Tiger (m)",
        "source_de": "<a href=\"https:\/\/de.wikipedia.org\/wiki\/Tiger\" target=\"_blank\"><img width=\"24\" height=\"24\" src=\"\/images\/poster\/edupack\/icon\/24-en-wiki.png\" \/><\/a>",
        "audio_de": "<audio src=\"https:\/\/www.w3schools.com\/html\/horse.mp3\" class=\"audioplay jp\"><\/audio>",
        "id": 20
    },
    {
        "name": "Unau",
        "source": "<a href=\"https:\/\/en.wikipedia.org\/wiki\/Two-toed_sloth\" target=\"_blank\"><img width=\"24\" height=\"24\" src=\"\/images\/poster\/edupack\/icon\/24-en-wiki.png\" \/><\/a>",
        "audio": "<audio src=\"https:\/\/www.w3schools.com\/html\/horse.mp3\" class=\"audioplay en\"><\/audio>",
        "name_jp": "\u30ca\u30de\u30b1\u30e2\u30ce",
        "source_jp": "<a href=\"https:\/\/ja.wikipedia.org\/wiki\/%E3%83%8A%E3%83%9E%E3%82%B1%E3%83%A2%E3%83%8E\" target=\"_blank\"><img width=\"24\" height=\"24\" src=\"\/images\/poster\/edupack\/icon\/24-jp-wiki.png\" \/><\/a>",
        "audio_jp": "<audio src=\"https:\/\/www.w3schools.com\/html\/horse.mp3\" class=\"audioplay jp\"><\/audio>",
        "name_de": "Unau (n)",
        "source_de": "<a href=\"https:\/\/de.wikipedia.org\/wiki\/Zweifinger-Faultiere\" target=\"_blank\"><img width=\"24\" height=\"24\" src=\"\/images\/poster\/edupack\/icon\/24-en-wiki.png\" \/><\/a>",
        "audio_de": "<audio src=\"https:\/\/www.w3schools.com\/html\/horse.mp3\" class=\"audioplay jp\"><\/audio>",
        "id": 21
    },
    {
        "name": "Viper",
        "source": "<a href=\"https:\/\/en.wikipedia.org\/wiki\/Viperidae\" target=\"_blank\"><img width=\"24\" height=\"24\" src=\"\/images\/poster\/edupack\/icon\/24-en-wiki.png\" \/><\/a>",
        "audio": "<audio src=\"https:\/\/www.w3schools.com\/html\/horse.mp3\" class=\"audioplay en\"><\/audio>",
        "name_jp": "\u30af\u30b5\u30ea\u30d8\u30d3",
        "source_jp": "<a href=\"https:\/\/ja.wikipedia.org\/wiki\/%E3%82%AF%E3%82%B5%E3%83%AA%E3%83%98%E3%83%93%E7%A7%91\" target=\"_blank\"><img width=\"24\" height=\"24\" src=\"\/images\/poster\/edupack\/icon\/24-jp-wiki.png\" \/><\/a>",
        "audio_jp": "<audio src=\"https:\/\/www.w3schools.com\/html\/horse.mp3\" class=\"audioplay jp\"><\/audio>",
        "name_de": "Vipern (f)",
        "source_de": "<a href=\"https:\/\/de.wikipedia.org\/wiki\/Vipern\" target=\"_blank\"><img width=\"24\" height=\"24\" src=\"\/images\/poster\/edupack\/icon\/24-en-wiki.png\" \/><\/a>",
        "audio_de": "<audio src=\"https:\/\/www.w3schools.com\/html\/horse.mp3\" class=\"audioplay jp\"><\/audio>",
        "id": 22
    },
    {
        "name": "Walrus",
        "source": "<a href=\"https:\/\/en.wikipedia.org\/wiki\/Walrus\" target=\"_blank\"><img width=\"24\" height=\"24\" src=\"\/images\/poster\/edupack\/icon\/24-en-wiki.png\" \/><\/a>",
        "audio": "<audio src=\"https:\/\/www.w3schools.com\/html\/horse.mp3\" class=\"audioplay en\"><\/audio>",
        "name_jp": "\u30bb\u30a4\u30a6\u30c1",
        "source_jp": "<a href=\"https:\/\/ja.wikipedia.org\/wiki\/%E3%82%BB%E3%82%A4%E3%82%A6%E3%83%81\" target=\"_blank\"><img width=\"24\" height=\"24\" src=\"\/images\/poster\/edupack\/icon\/24-jp-wiki.png\" \/><\/a>",
        "audio_jp": "<audio src=\"https:\/\/www.w3schools.com\/html\/horse.mp3\" class=\"audioplay jp\"><\/audio>",
        "name_de": "Walro\u00df (n)",
        "source_de": "<a href=\"https:\/\/de.wikipedia.org\/wiki\/Walross\" target=\"_blank\"><img width=\"24\" height=\"24\" src=\"\/images\/poster\/edupack\/icon\/24-en-wiki.png\" \/><\/a>",
        "audio_de": "<audio src=\"https:\/\/www.w3schools.com\/html\/horse.mp3\" class=\"audioplay jp\"><\/audio>",
        "id": 23
    },
    {
        "name": "Xianglong",
        "source": "<a href=\"https:\/\/en.wikipedia.org\/wiki\/Xianglong\" target=\"_blank\"><img width=\"24\" height=\"24\" src=\"\/images\/poster\/edupack\/icon\/24-en-wiki.png\" \/><\/a>",
        "audio": "<audio src=\"https:\/\/www.w3schools.com\/html\/horse.mp3\" class=\"audioplay en\"><\/audio>",
        "name_jp": "\u30b7\u30e3\u30f3\u30ed\u30f3",
        "source_jp": "<a href=\"https:\/\/ja.wikipedia.org\/wiki\/%E3%83%89%E3%83%AD%E3%83%9E%E3%82%A8%E3%82%AA%E3%82%B5%E3%82%A6%E3%83%AB%E3%82%B9%E7%A7%91\" target=\"_blank\"><img width=\"24\" height=\"24\" src=\"\/images\/poster\/edupack\/icon\/24-jp-wiki.png\" \/><\/a>",
        "audio_jp": "<audio src=\"https:\/\/www.w3schools.com\/html\/horse.mp3\" class=\"audioplay jp\"><\/audio>",
        "name_de": "Xianglong",
        "source_de": "<a href=\"https:\/\/de.wikipedia.org\/wiki\/Xianglong_(Gattung)\" target=\"_blank\"><img width=\"24\" height=\"24\" src=\"\/images\/poster\/edupack\/icon\/24-en-wiki.png\" \/><\/a>",
        "audio_de": "<audio src=\"https:\/\/www.w3schools.com\/html\/horse.mp3\" class=\"audioplay jp\"><\/audio>",
        "id": 24
    },
    {
        "name": "Yak",
        "source": "<a href=\"https:\/\/en.wikipedia.org\/wiki\/Domestic_yak\" target=\"_blank\"><img width=\"24\" height=\"24\" src=\"\/images\/poster\/edupack\/icon\/24-en-wiki.png\" \/><\/a>",
        "audio": "<audio src=\"https:\/\/www.w3schools.com\/html\/horse.mp3\" class=\"audioplay en\"><\/audio>",
        "name_jp": "\u30e4\u30af",
        "source_jp": "<a href=\"https:\/\/ja.wikipedia.org\/wiki\/%E3%83%A4%E3%82%AF\" target=\"_blank\"><img width=\"24\" height=\"24\" src=\"\/images\/poster\/edupack\/icon\/24-jp-wiki.png\" \/><\/a>",
        "audio_jp": "<audio src=\"https:\/\/www.w3schools.com\/html\/horse.mp3\" class=\"audioplay jp\"><\/audio>",
        "name_de": "Yak (m) (n)",
        "source_de": "<a href=\"https:\/\/de.wikipedia.org\/wiki\/Yak\" target=\"_blank\"><img width=\"24\" height=\"24\" src=\"\/images\/poster\/edupack\/icon\/24-en-wiki.png\" \/><\/a>",
        "audio_de": "<audio src=\"https:\/\/www.w3schools.com\/html\/horse.mp3\" class=\"audioplay jp\"><\/audio>",
        "id": 25
    },
    {
        "name": "Zebra",
        "source": "<a href=\"https:\/\/en.wikipedia.org\/wiki\/Zebra\" target=\"_blank\"><img width=\"24\" height=\"24\" src=\"\/images\/poster\/edupack\/icon\/24-en-wiki.png\" \/><\/a>",
        "audio": "<audio src=\"https:\/\/www.w3schools.com\/html\/horse.mp3\" class=\"audioplay en\"><\/audio>",
        "name_jp": "\u30b7\u30de\u30a6\u30de",
        "source_jp": "<a href=\"https:\/\/ja.wikipedia.org\/wiki\/%E3%82%B7%E3%83%9E%E3%82%A6%E3%83%9E\" target=\"_blank\"><img width=\"24\" height=\"24\" src=\"\/images\/poster\/edupack\/icon\/24-jp-wiki.png\" \/><\/a>",
        "audio_jp": "<audio src=\"https:\/\/www.w3schools.com\/html\/horse.mp3\" class=\"audioplay jp\"><\/audio>",
        "name_de": "Zebra (n)",
        "source_de": "<a href=\"https:\/\/de.wikipedia.org\/wiki\/Zebras\" target=\"_blank\"><img width=\"24\" height=\"24\" src=\"\/images\/poster\/edupack\/icon\/24-en-wiki.png\" \/><\/a>",
        "audio_de": "<audio src=\"https:\/\/www.w3schools.com\/html\/horse.mp3\" class=\"audioplay jp\"><\/audio>",
        "id": 26
    },
    {
        "name": "Crow",
        "source": "<a href=\"https:\/\/en.wikipedia.org\/wiki\/Carrion_crow\" target=\"_blank\"><img width=\"24\" height=\"24\" src=\"\/images\/poster\/edupack\/icon\/24-en-wiki.png\" \/><\/a>",
        "audio": "<audio src=\"https:\/\/www.w3schools.com\/html\/horse.mp3\" class=\"audioplay en\"><\/audio>",
        "name_jp": "\u30ab\u30e9\u30b9",
        "source_jp": "<a href=\"https:\/\/ja.wikipedia.org\/wiki\/%E3%82%AB%E3%83%A9%E3%82%B9\" target=\"_blank\"><img width=\"24\" height=\"24\" src=\"\/images\/poster\/edupack\/icon\/24-jp-wiki.png\" \/><\/a>",
        "audio_jp": "<audio src=\"https:\/\/www.w3schools.com\/html\/horse.mp3\" class=\"audioplay jp\"><\/audio>",
        "name_de": "Kr\u00e4he (f)",
        "source_de": "<a href=\"https:\/\/de.wikipedia.org\/wiki\/Aaskr%C3%A4he\" target=\"_blank\"><img width=\"24\" height=\"24\" src=\"\/images\/poster\/edupack\/icon\/24-en-wiki.png\" \/><\/a>",
        "audio_de": "<audio src=\"https:\/\/www.w3schools.com\/html\/horse.mp3\" class=\"audioplay jp\"><\/audio>",
        "id": 27
    },
    {
        "name": "Seagull",
        "source": "<a href=\"https:\/\/en.wikipedia.org\/wiki\/Gull\" target=\"_blank\"><img width=\"24\" height=\"24\" src=\"\/images\/poster\/edupack\/icon\/24-en-wiki.png\" \/><\/a>",
        "audio": "<audio src=\"https:\/\/www.w3schools.com\/html\/horse.mp3\" class=\"audioplay en\"><\/audio>",
        "name_jp": "\u30ab\u30e2\u30e1",
        "source_jp": "<a href=\"https:\/\/ja.wikipedia.org\/wiki\/%E3%82%AB%E3%83%A2%E3%83%A1\" target=\"_blank\"><img width=\"24\" height=\"24\" src=\"\/images\/poster\/edupack\/icon\/24-jp-wiki.png\" \/><\/a>",
        "audio_jp": "<audio src=\"https:\/\/www.w3schools.com\/html\/horse.mp3\" class=\"audioplay jp\"><\/audio>",
        "name_de": "M\u00f6wen (f)",
        "source_de": "<a href=\"https:\/\/de.wikipedia.org\/wiki\/M%C3%B6wen\" target=\"_blank\"><img width=\"24\" height=\"24\" src=\"\/images\/poster\/edupack\/icon\/24-en-wiki.png\" \/><\/a>",
        "audio_de": "<audio src=\"https:\/\/www.w3schools.com\/html\/horse.mp3\" class=\"audioplay jp\"><\/audio>",
        "id": 28
    },
    {
        "name": "Chick",
        "source": "<a href=\"https:\/\/en.wikipedia.org\/wiki\/Chicken\" target=\"_blank\"><img width=\"24\" height=\"24\" src=\"\/images\/poster\/edupack\/icon\/24-en-wiki.png\" \/><\/a>",
        "audio": "<audio src=\"https:\/\/www.w3schools.com\/html\/horse.mp3\" class=\"audioplay en\"><\/audio>",
        "name_jp": "\u3072\u3088\u3053",
        "source_jp": "<a href=\"https:\/\/ja.wikipedia.org\/wiki\/%E3%81%B2%E3%82%88%E3%81%93\" target=\"_blank\"><img width=\"24\" height=\"24\" src=\"\/images\/poster\/edupack\/icon\/24-jp-wiki.png\" \/><\/a>",
        "audio_jp": "<audio src=\"https:\/\/www.w3schools.com\/html\/horse.mp3\" class=\"audioplay jp\"><\/audio>",
        "name_de": "K\u00fcken (n)",
        "source_de": "<a href=\"https:\/\/de.wikipedia.org\/wiki\/K%C3%BCken\" target=\"_blank\"><img width=\"24\" height=\"24\" src=\"\/images\/poster\/edupack\/icon\/24-en-wiki.png\" \/><\/a>",
        "audio_de": "<audio src=\"https:\/\/www.w3schools.com\/html\/horse.mp3\" class=\"audioplay jp\"><\/audio>",
        "id": 29
    },
    {
        "name": "Ostrich",
        "source": "<a href=\"https:\/\/en.wikipedia.org\/wiki\/Ostrich\" target=\"_blank\"><img width=\"24\" height=\"24\" src=\"\/images\/poster\/edupack\/icon\/24-en-wiki.png\" \/><\/a>",
        "audio": "<audio src=\"https:\/\/www.w3schools.com\/html\/horse.mp3\" class=\"audioplay en\"><\/audio>",
        "name_jp": "\u30c0\u30c1\u30e7\u30a6",
        "source_jp": "<a href=\"https:\/\/ja.wikipedia.org\/wiki\/%E3%83%80%E3%83%81%E3%83%A7%E3%82%A6\" target=\"_blank\"><img width=\"24\" height=\"24\" src=\"\/images\/poster\/edupack\/icon\/24-jp-wiki.png\" \/><\/a>",
        "audio_jp": "<audio src=\"https:\/\/www.w3schools.com\/html\/horse.mp3\" class=\"audioplay jp\"><\/audio>",
        "name_de": "Strau\u00df (m)",
        "source_de": "<a href=\"https:\/\/de.wikipedia.org\/wiki\/Strau%C3%9Fe_(Gattung)\" target=\"_blank\"><img width=\"24\" height=\"24\" src=\"\/images\/poster\/edupack\/icon\/24-en-wiki.png\" \/><\/a>",
        "audio_de": "<audio src=\"https:\/\/www.w3schools.com\/html\/horse.mp3\" class=\"audioplay jp\"><\/audio>",
        "id": 30
    },
    {
        "name": "A",
        "source": "<a href=\"\" target=\"_blank\"><img width=\"24\" height=\"24\" src=\"\/images\/poster\/edupack\/icon\/24-en-wiki.png\" \/><\/a>",
        "audio": "<audio src=\"https:\/\/www.w3schools.com\/html\/horse.mp3\" class=\"audioplay en\"><\/audio>",
        "name_jp": null,
        "source_jp": "<a href=\"\" target=\"_blank\"><img width=\"24\" height=\"24\" src=\"\/images\/poster\/edupack\/icon\/24-jp-wiki.png\" \/><\/a>",
        "audio_jp": "<audio src=\"https:\/\/www.w3schools.com\/html\/horse.mp3\" class=\"audioplay jp\"><\/audio>",
        "name_de": "A",
        "source_de": "<a href=\"\" target=\"_blank\"><img width=\"24\" height=\"24\" src=\"\/images\/poster\/edupack\/icon\/24-en-wiki.png\" \/><\/a>",
        "audio_de": "<audio src=\"https:\/\/www.w3schools.com\/html\/horse.mp3\" class=\"audioplay jp\"><\/audio>",
        "id": 31
    },
    {
        "name": "B",
        "source": "<a href=\"\" target=\"_blank\"><img width=\"24\" height=\"24\" src=\"\/images\/poster\/edupack\/icon\/24-en-wiki.png\" \/><\/a>",
        "audio": "<audio src=\"https:\/\/www.w3schools.com\/html\/horse.mp3\" class=\"audioplay en\"><\/audio>",
        "name_jp": null,
        "source_jp": "<a href=\"\" target=\"_blank\"><img width=\"24\" height=\"24\" src=\"\/images\/poster\/edupack\/icon\/24-jp-wiki.png\" \/><\/a>",
        "audio_jp": "<audio src=\"https:\/\/www.w3schools.com\/html\/horse.mp3\" class=\"audioplay jp\"><\/audio>",
        "name_de": "B",
        "source_de": "<a href=\"\" target=\"_blank\"><img width=\"24\" height=\"24\" src=\"\/images\/poster\/edupack\/icon\/24-en-wiki.png\" \/><\/a>",
        "audio_de": "<audio src=\"https:\/\/www.w3schools.com\/html\/horse.mp3\" class=\"audioplay jp\"><\/audio>",
        "id": 32
    },
    {
        "name": "C",
        "source": "<a href=\"\" target=\"_blank\"><img width=\"24\" height=\"24\" src=\"\/images\/poster\/edupack\/icon\/24-en-wiki.png\" \/><\/a>",
        "audio": "<audio src=\"https:\/\/www.w3schools.com\/html\/horse.mp3\" class=\"audioplay en\"><\/audio>",
        "name_jp": null,
        "source_jp": "<a href=\"\" target=\"_blank\"><img width=\"24\" height=\"24\" src=\"\/images\/poster\/edupack\/icon\/24-jp-wiki.png\" \/><\/a>",
        "audio_jp": "<audio src=\"https:\/\/www.w3schools.com\/html\/horse.mp3\" class=\"audioplay jp\"><\/audio>",
        "name_de": "C",
        "source_de": "<a href=\"\" target=\"_blank\"><img width=\"24\" height=\"24\" src=\"\/images\/poster\/edupack\/icon\/24-en-wiki.png\" \/><\/a>",
        "audio_de": "<audio src=\"https:\/\/www.w3schools.com\/html\/horse.mp3\" class=\"audioplay jp\"><\/audio>",
        "id": 33
    },
    {
        "name": "D",
        "source": "<a href=\"\" target=\"_blank\"><img width=\"24\" height=\"24\" src=\"\/images\/poster\/edupack\/icon\/24-en-wiki.png\" \/><\/a>",
        "audio": "<audio src=\"https:\/\/www.w3schools.com\/html\/horse.mp3\" class=\"audioplay en\"><\/audio>",
        "name_jp": null,
        "source_jp": "<a href=\"\" target=\"_blank\"><img width=\"24\" height=\"24\" src=\"\/images\/poster\/edupack\/icon\/24-jp-wiki.png\" \/><\/a>",
        "audio_jp": "<audio src=\"https:\/\/www.w3schools.com\/html\/horse.mp3\" class=\"audioplay jp\"><\/audio>",
        "name_de": "D",
        "source_de": "<a href=\"\" target=\"_blank\"><img width=\"24\" height=\"24\" src=\"\/images\/poster\/edupack\/icon\/24-en-wiki.png\" \/><\/a>",
        "audio_de": "<audio src=\"https:\/\/www.w3schools.com\/html\/horse.mp3\" class=\"audioplay jp\"><\/audio>",
        "id": 34
    },
    {
        "name": "E",
        "source": "<a href=\"\" target=\"_blank\"><img width=\"24\" height=\"24\" src=\"\/images\/poster\/edupack\/icon\/24-en-wiki.png\" \/><\/a>",
        "audio": "<audio src=\"https:\/\/www.w3schools.com\/html\/horse.mp3\" class=\"audioplay en\"><\/audio>",
        "name_jp": null,
        "source_jp": "<a href=\"\" target=\"_blank\"><img width=\"24\" height=\"24\" src=\"\/images\/poster\/edupack\/icon\/24-jp-wiki.png\" \/><\/a>",
        "audio_jp": "<audio src=\"https:\/\/www.w3schools.com\/html\/horse.mp3\" class=\"audioplay jp\"><\/audio>",
        "name_de": "E",
        "source_de": "<a href=\"\" target=\"_blank\"><img width=\"24\" height=\"24\" src=\"\/images\/poster\/edupack\/icon\/24-en-wiki.png\" \/><\/a>",
        "audio_de": "<audio src=\"https:\/\/www.w3schools.com\/html\/horse.mp3\" class=\"audioplay jp\"><\/audio>",
        "id": 35
    },
    {
        "name": "F",
        "source": "<a href=\"\" target=\"_blank\"><img width=\"24\" height=\"24\" src=\"\/images\/poster\/edupack\/icon\/24-en-wiki.png\" \/><\/a>",
        "audio": "<audio src=\"https:\/\/www.w3schools.com\/html\/horse.mp3\" class=\"audioplay en\"><\/audio>",
        "name_jp": null,
        "source_jp": "<a href=\"\" target=\"_blank\"><img width=\"24\" height=\"24\" src=\"\/images\/poster\/edupack\/icon\/24-jp-wiki.png\" \/><\/a>",
        "audio_jp": "<audio src=\"https:\/\/www.w3schools.com\/html\/horse.mp3\" class=\"audioplay jp\"><\/audio>",
        "name_de": "F",
        "source_de": "<a href=\"\" target=\"_blank\"><img width=\"24\" height=\"24\" src=\"\/images\/poster\/edupack\/icon\/24-en-wiki.png\" \/><\/a>",
        "audio_de": "<audio src=\"https:\/\/www.w3schools.com\/html\/horse.mp3\" class=\"audioplay jp\"><\/audio>",
        "id": 36
    },
    {
        "name": "G",
        "source": "<a href=\"\" target=\"_blank\"><img width=\"24\" height=\"24\" src=\"\/images\/poster\/edupack\/icon\/24-en-wiki.png\" \/><\/a>",
        "audio": "<audio src=\"https:\/\/www.w3schools.com\/html\/horse.mp3\" class=\"audioplay en\"><\/audio>",
        "name_jp": null,
        "source_jp": "<a href=\"\" target=\"_blank\"><img width=\"24\" height=\"24\" src=\"\/images\/poster\/edupack\/icon\/24-jp-wiki.png\" \/><\/a>",
        "audio_jp": "<audio src=\"https:\/\/www.w3schools.com\/html\/horse.mp3\" class=\"audioplay jp\"><\/audio>",
        "name_de": "G",
        "source_de": "<a href=\"\" target=\"_blank\"><img width=\"24\" height=\"24\" src=\"\/images\/poster\/edupack\/icon\/24-en-wiki.png\" \/><\/a>",
        "audio_de": "<audio src=\"https:\/\/www.w3schools.com\/html\/horse.mp3\" class=\"audioplay jp\"><\/audio>",
        "id": 37
    },
    {
        "name": "H",
        "source": "<a href=\"\" target=\"_blank\"><img width=\"24\" height=\"24\" src=\"\/images\/poster\/edupack\/icon\/24-en-wiki.png\" \/><\/a>",
        "audio": "<audio src=\"https:\/\/www.w3schools.com\/html\/horse.mp3\" class=\"audioplay en\"><\/audio>",
        "name_jp": null,
        "source_jp": "<a href=\"\" target=\"_blank\"><img width=\"24\" height=\"24\" src=\"\/images\/poster\/edupack\/icon\/24-jp-wiki.png\" \/><\/a>",
        "audio_jp": "<audio src=\"https:\/\/www.w3schools.com\/html\/horse.mp3\" class=\"audioplay jp\"><\/audio>",
        "name_de": "H",
        "source_de": "<a href=\"\" target=\"_blank\"><img width=\"24\" height=\"24\" src=\"\/images\/poster\/edupack\/icon\/24-en-wiki.png\" \/><\/a>",
        "audio_de": "<audio src=\"https:\/\/www.w3schools.com\/html\/horse.mp3\" class=\"audioplay jp\"><\/audio>",
        "id": 38
    },
    {
        "name": "I",
        "source": "<a href=\"\" target=\"_blank\"><img width=\"24\" height=\"24\" src=\"\/images\/poster\/edupack\/icon\/24-en-wiki.png\" \/><\/a>",
        "audio": "<audio src=\"https:\/\/www.w3schools.com\/html\/horse.mp3\" class=\"audioplay en\"><\/audio>",
        "name_jp": null,
        "source_jp": "<a href=\"\" target=\"_blank\"><img width=\"24\" height=\"24\" src=\"\/images\/poster\/edupack\/icon\/24-jp-wiki.png\" \/><\/a>",
        "audio_jp": "<audio src=\"https:\/\/www.w3schools.com\/html\/horse.mp3\" class=\"audioplay jp\"><\/audio>",
        "name_de": "I",
        "source_de": "<a href=\"\" target=\"_blank\"><img width=\"24\" height=\"24\" src=\"\/images\/poster\/edupack\/icon\/24-en-wiki.png\" \/><\/a>",
        "audio_de": "<audio src=\"https:\/\/www.w3schools.com\/html\/horse.mp3\" class=\"audioplay jp\"><\/audio>",
        "id": 39
    },
    {
        "name": "J",
        "source": "<a href=\"\" target=\"_blank\"><img width=\"24\" height=\"24\" src=\"\/images\/poster\/edupack\/icon\/24-en-wiki.png\" \/><\/a>",
        "audio": "<audio src=\"https:\/\/www.w3schools.com\/html\/horse.mp3\" class=\"audioplay en\"><\/audio>",
        "name_jp": null,
        "source_jp": "<a href=\"\" target=\"_blank\"><img width=\"24\" height=\"24\" src=\"\/images\/poster\/edupack\/icon\/24-jp-wiki.png\" \/><\/a>",
        "audio_jp": "<audio src=\"https:\/\/www.w3schools.com\/html\/horse.mp3\" class=\"audioplay jp\"><\/audio>",
        "name_de": "J",
        "source_de": "<a href=\"\" target=\"_blank\"><img width=\"24\" height=\"24\" src=\"\/images\/poster\/edupack\/icon\/24-en-wiki.png\" \/><\/a>",
        "audio_de": "<audio src=\"https:\/\/www.w3schools.com\/html\/horse.mp3\" class=\"audioplay jp\"><\/audio>",
        "id": 40
    },
    {
        "name": "K",
        "source": "<a href=\"\" target=\"_blank\"><img width=\"24\" height=\"24\" src=\"\/images\/poster\/edupack\/icon\/24-en-wiki.png\" \/><\/a>",
        "audio": "<audio src=\"https:\/\/www.w3schools.com\/html\/horse.mp3\" class=\"audioplay en\"><\/audio>",
        "name_jp": null,
        "source_jp": "<a href=\"\" target=\"_blank\"><img width=\"24\" height=\"24\" src=\"\/images\/poster\/edupack\/icon\/24-jp-wiki.png\" \/><\/a>",
        "audio_jp": "<audio src=\"https:\/\/www.w3schools.com\/html\/horse.mp3\" class=\"audioplay jp\"><\/audio>",
        "name_de": "K",
        "source_de": "<a href=\"\" target=\"_blank\"><img width=\"24\" height=\"24\" src=\"\/images\/poster\/edupack\/icon\/24-en-wiki.png\" \/><\/a>",
        "audio_de": "<audio src=\"https:\/\/www.w3schools.com\/html\/horse.mp3\" class=\"audioplay jp\"><\/audio>",
        "id": 41
    },
    {
        "name": "L",
        "source": "<a href=\"\" target=\"_blank\"><img width=\"24\" height=\"24\" src=\"\/images\/poster\/edupack\/icon\/24-en-wiki.png\" \/><\/a>",
        "audio": "<audio src=\"https:\/\/www.w3schools.com\/html\/horse.mp3\" class=\"audioplay en\"><\/audio>",
        "name_jp": null,
        "source_jp": "<a href=\"\" target=\"_blank\"><img width=\"24\" height=\"24\" src=\"\/images\/poster\/edupack\/icon\/24-jp-wiki.png\" \/><\/a>",
        "audio_jp": "<audio src=\"https:\/\/www.w3schools.com\/html\/horse.mp3\" class=\"audioplay jp\"><\/audio>",
        "name_de": "L",
        "source_de": "<a href=\"\" target=\"_blank\"><img width=\"24\" height=\"24\" src=\"\/images\/poster\/edupack\/icon\/24-en-wiki.png\" \/><\/a>",
        "audio_de": "<audio src=\"https:\/\/www.w3schools.com\/html\/horse.mp3\" class=\"audioplay jp\"><\/audio>",
        "id": 42
    },
    {
        "name": "M",
        "source": "<a href=\"\" target=\"_blank\"><img width=\"24\" height=\"24\" src=\"\/images\/poster\/edupack\/icon\/24-en-wiki.png\" \/><\/a>",
        "audio": "<audio src=\"https:\/\/www.w3schools.com\/html\/horse.mp3\" class=\"audioplay en\"><\/audio>",
        "name_jp": null,
        "source_jp": "<a href=\"\" target=\"_blank\"><img width=\"24\" height=\"24\" src=\"\/images\/poster\/edupack\/icon\/24-jp-wiki.png\" \/><\/a>",
        "audio_jp": "<audio src=\"https:\/\/www.w3schools.com\/html\/horse.mp3\" class=\"audioplay jp\"><\/audio>",
        "name_de": "M",
        "source_de": "<a href=\"\" target=\"_blank\"><img width=\"24\" height=\"24\" src=\"\/images\/poster\/edupack\/icon\/24-en-wiki.png\" \/><\/a>",
        "audio_de": "<audio src=\"https:\/\/www.w3schools.com\/html\/horse.mp3\" class=\"audioplay jp\"><\/audio>",
        "id": 43
    },
    {
        "name": "N",
        "source": "<a href=\"\" target=\"_blank\"><img width=\"24\" height=\"24\" src=\"\/images\/poster\/edupack\/icon\/24-en-wiki.png\" \/><\/a>",
        "audio": "<audio src=\"https:\/\/www.w3schools.com\/html\/horse.mp3\" class=\"audioplay en\"><\/audio>",
        "name_jp": null,
        "source_jp": "<a href=\"\" target=\"_blank\"><img width=\"24\" height=\"24\" src=\"\/images\/poster\/edupack\/icon\/24-jp-wiki.png\" \/><\/a>",
        "audio_jp": "<audio src=\"https:\/\/www.w3schools.com\/html\/horse.mp3\" class=\"audioplay jp\"><\/audio>",
        "name_de": "N",
        "source_de": "<a href=\"\" target=\"_blank\"><img width=\"24\" height=\"24\" src=\"\/images\/poster\/edupack\/icon\/24-en-wiki.png\" \/><\/a>",
        "audio_de": "<audio src=\"https:\/\/www.w3schools.com\/html\/horse.mp3\" class=\"audioplay jp\"><\/audio>",
        "id": 44
    },
    {
        "name": "O",
        "source": "<a href=\"\" target=\"_blank\"><img width=\"24\" height=\"24\" src=\"\/images\/poster\/edupack\/icon\/24-en-wiki.png\" \/><\/a>",
        "audio": "<audio src=\"https:\/\/www.w3schools.com\/html\/horse.mp3\" class=\"audioplay en\"><\/audio>",
        "name_jp": null,
        "source_jp": "<a href=\"\" target=\"_blank\"><img width=\"24\" height=\"24\" src=\"\/images\/poster\/edupack\/icon\/24-jp-wiki.png\" \/><\/a>",
        "audio_jp": "<audio src=\"https:\/\/www.w3schools.com\/html\/horse.mp3\" class=\"audioplay jp\"><\/audio>",
        "name_de": "O",
        "source_de": "<a href=\"\" target=\"_blank\"><img width=\"24\" height=\"24\" src=\"\/images\/poster\/edupack\/icon\/24-en-wiki.png\" \/><\/a>",
        "audio_de": "<audio src=\"https:\/\/www.w3schools.com\/html\/horse.mp3\" class=\"audioplay jp\"><\/audio>",
        "id": 45
    },
    {
        "name": "P",
        "source": "<a href=\"\" target=\"_blank\"><img width=\"24\" height=\"24\" src=\"\/images\/poster\/edupack\/icon\/24-en-wiki.png\" \/><\/a>",
        "audio": "<audio src=\"https:\/\/www.w3schools.com\/html\/horse.mp3\" class=\"audioplay en\"><\/audio>",
        "name_jp": null,
        "source_jp": "<a href=\"\" target=\"_blank\"><img width=\"24\" height=\"24\" src=\"\/images\/poster\/edupack\/icon\/24-jp-wiki.png\" \/><\/a>",
        "audio_jp": "<audio src=\"https:\/\/www.w3schools.com\/html\/horse.mp3\" class=\"audioplay jp\"><\/audio>",
        "name_de": "P",
        "source_de": "<a href=\"\" target=\"_blank\"><img width=\"24\" height=\"24\" src=\"\/images\/poster\/edupack\/icon\/24-en-wiki.png\" \/><\/a>",
        "audio_de": "<audio src=\"https:\/\/www.w3schools.com\/html\/horse.mp3\" class=\"audioplay jp\"><\/audio>",
        "id": 46
    },
    {
        "name": "Q",
        "source": "<a href=\"\" target=\"_blank\"><img width=\"24\" height=\"24\" src=\"\/images\/poster\/edupack\/icon\/24-en-wiki.png\" \/><\/a>",
        "audio": "<audio src=\"https:\/\/www.w3schools.com\/html\/horse.mp3\" class=\"audioplay en\"><\/audio>",
        "name_jp": null,
        "source_jp": "<a href=\"\" target=\"_blank\"><img width=\"24\" height=\"24\" src=\"\/images\/poster\/edupack\/icon\/24-jp-wiki.png\" \/><\/a>",
        "audio_jp": "<audio src=\"https:\/\/www.w3schools.com\/html\/horse.mp3\" class=\"audioplay jp\"><\/audio>",
        "name_de": "Q",
        "source_de": "<a href=\"\" target=\"_blank\"><img width=\"24\" height=\"24\" src=\"\/images\/poster\/edupack\/icon\/24-en-wiki.png\" \/><\/a>",
        "audio_de": "<audio src=\"https:\/\/www.w3schools.com\/html\/horse.mp3\" class=\"audioplay jp\"><\/audio>",
        "id": 47
    },
    {
        "name": "R",
        "source": "<a href=\"\" target=\"_blank\"><img width=\"24\" height=\"24\" src=\"\/images\/poster\/edupack\/icon\/24-en-wiki.png\" \/><\/a>",
        "audio": "<audio src=\"https:\/\/www.w3schools.com\/html\/horse.mp3\" class=\"audioplay en\"><\/audio>",
        "name_jp": null,
        "source_jp": "<a href=\"\" target=\"_blank\"><img width=\"24\" height=\"24\" src=\"\/images\/poster\/edupack\/icon\/24-jp-wiki.png\" \/><\/a>",
        "audio_jp": "<audio src=\"https:\/\/www.w3schools.com\/html\/horse.mp3\" class=\"audioplay jp\"><\/audio>",
        "name_de": "R",
        "source_de": "<a href=\"\" target=\"_blank\"><img width=\"24\" height=\"24\" src=\"\/images\/poster\/edupack\/icon\/24-en-wiki.png\" \/><\/a>",
        "audio_de": "<audio src=\"https:\/\/www.w3schools.com\/html\/horse.mp3\" class=\"audioplay jp\"><\/audio>",
        "id": 48
    },
    {
        "name": "S",
        "source": "<a href=\"\" target=\"_blank\"><img width=\"24\" height=\"24\" src=\"\/images\/poster\/edupack\/icon\/24-en-wiki.png\" \/><\/a>",
        "audio": "<audio src=\"https:\/\/www.w3schools.com\/html\/horse.mp3\" class=\"audioplay en\"><\/audio>",
        "name_jp": null,
        "source_jp": "<a href=\"\" target=\"_blank\"><img width=\"24\" height=\"24\" src=\"\/images\/poster\/edupack\/icon\/24-jp-wiki.png\" \/><\/a>",
        "audio_jp": "<audio src=\"https:\/\/www.w3schools.com\/html\/horse.mp3\" class=\"audioplay jp\"><\/audio>",
        "name_de": "S",
        "source_de": "<a href=\"\" target=\"_blank\"><img width=\"24\" height=\"24\" src=\"\/images\/poster\/edupack\/icon\/24-en-wiki.png\" \/><\/a>",
        "audio_de": "<audio src=\"https:\/\/www.w3schools.com\/html\/horse.mp3\" class=\"audioplay jp\"><\/audio>",
        "id": 49
    },
    {
        "name": "T",
        "source": "<a href=\"\" target=\"_blank\"><img width=\"24\" height=\"24\" src=\"\/images\/poster\/edupack\/icon\/24-en-wiki.png\" \/><\/a>",
        "audio": "<audio src=\"https:\/\/www.w3schools.com\/html\/horse.mp3\" class=\"audioplay en\"><\/audio>",
        "name_jp": null,
        "source_jp": "<a href=\"\" target=\"_blank\"><img width=\"24\" height=\"24\" src=\"\/images\/poster\/edupack\/icon\/24-jp-wiki.png\" \/><\/a>",
        "audio_jp": "<audio src=\"https:\/\/www.w3schools.com\/html\/horse.mp3\" class=\"audioplay jp\"><\/audio>",
        "name_de": "T",
        "source_de": "<a href=\"\" target=\"_blank\"><img width=\"24\" height=\"24\" src=\"\/images\/poster\/edupack\/icon\/24-en-wiki.png\" \/><\/a>",
        "audio_de": "<audio src=\"https:\/\/www.w3schools.com\/html\/horse.mp3\" class=\"audioplay jp\"><\/audio>",
        "id": 50
    },
    {
        "name": "U",
        "source": "<a href=\"\" target=\"_blank\"><img width=\"24\" height=\"24\" src=\"\/images\/poster\/edupack\/icon\/24-en-wiki.png\" \/><\/a>",
        "audio": "<audio src=\"https:\/\/www.w3schools.com\/html\/horse.mp3\" class=\"audioplay en\"><\/audio>",
        "name_jp": null,
        "source_jp": "<a href=\"\" target=\"_blank\"><img width=\"24\" height=\"24\" src=\"\/images\/poster\/edupack\/icon\/24-jp-wiki.png\" \/><\/a>",
        "audio_jp": "<audio src=\"https:\/\/www.w3schools.com\/html\/horse.mp3\" class=\"audioplay jp\"><\/audio>",
        "name_de": "U",
        "source_de": "<a href=\"\" target=\"_blank\"><img width=\"24\" height=\"24\" src=\"\/images\/poster\/edupack\/icon\/24-en-wiki.png\" \/><\/a>",
        "audio_de": "<audio src=\"https:\/\/www.w3schools.com\/html\/horse.mp3\" class=\"audioplay jp\"><\/audio>",
        "id": 51
    },
    {
        "name": "V",
        "source": "<a href=\"\" target=\"_blank\"><img width=\"24\" height=\"24\" src=\"\/images\/poster\/edupack\/icon\/24-en-wiki.png\" \/><\/a>",
        "audio": "<audio src=\"https:\/\/www.w3schools.com\/html\/horse.mp3\" class=\"audioplay en\"><\/audio>",
        "name_jp": null,
        "source_jp": "<a href=\"\" target=\"_blank\"><img width=\"24\" height=\"24\" src=\"\/images\/poster\/edupack\/icon\/24-jp-wiki.png\" \/><\/a>",
        "audio_jp": "<audio src=\"https:\/\/www.w3schools.com\/html\/horse.mp3\" class=\"audioplay jp\"><\/audio>",
        "name_de": "V",
        "source_de": "<a href=\"\" target=\"_blank\"><img width=\"24\" height=\"24\" src=\"\/images\/poster\/edupack\/icon\/24-en-wiki.png\" \/><\/a>",
        "audio_de": "<audio src=\"https:\/\/www.w3schools.com\/html\/horse.mp3\" class=\"audioplay jp\"><\/audio>",
        "id": 52
    },
    {
        "name": "W",
        "source": "<a href=\"\" target=\"_blank\"><img width=\"24\" height=\"24\" src=\"\/images\/poster\/edupack\/icon\/24-en-wiki.png\" \/><\/a>",
        "audio": "<audio src=\"https:\/\/www.w3schools.com\/html\/horse.mp3\" class=\"audioplay en\"><\/audio>",
        "name_jp": null,
        "source_jp": "<a href=\"\" target=\"_blank\"><img width=\"24\" height=\"24\" src=\"\/images\/poster\/edupack\/icon\/24-jp-wiki.png\" \/><\/a>",
        "audio_jp": "<audio src=\"https:\/\/www.w3schools.com\/html\/horse.mp3\" class=\"audioplay jp\"><\/audio>",
        "name_de": "W",
        "source_de": "<a href=\"\" target=\"_blank\"><img width=\"24\" height=\"24\" src=\"\/images\/poster\/edupack\/icon\/24-en-wiki.png\" \/><\/a>",
        "audio_de": "<audio src=\"https:\/\/www.w3schools.com\/html\/horse.mp3\" class=\"audioplay jp\"><\/audio>",
        "id": 53
    },
    {
        "name": "X",
        "source": "<a href=\"\" target=\"_blank\"><img width=\"24\" height=\"24\" src=\"\/images\/poster\/edupack\/icon\/24-en-wiki.png\" \/><\/a>",
        "audio": "<audio src=\"https:\/\/www.w3schools.com\/html\/horse.mp3\" class=\"audioplay en\"><\/audio>",
        "name_jp": null,
        "source_jp": "<a href=\"\" target=\"_blank\"><img width=\"24\" height=\"24\" src=\"\/images\/poster\/edupack\/icon\/24-jp-wiki.png\" \/><\/a>",
        "audio_jp": "<audio src=\"https:\/\/www.w3schools.com\/html\/horse.mp3\" class=\"audioplay jp\"><\/audio>",
        "name_de": "X",
        "source_de": "<a href=\"\" target=\"_blank\"><img width=\"24\" height=\"24\" src=\"\/images\/poster\/edupack\/icon\/24-en-wiki.png\" \/><\/a>",
        "audio_de": "<audio src=\"https:\/\/www.w3schools.com\/html\/horse.mp3\" class=\"audioplay jp\"><\/audio>",
        "id": 54
    },
    {
        "name": "Y",
        "source": "<a href=\"\" target=\"_blank\"><img width=\"24\" height=\"24\" src=\"\/images\/poster\/edupack\/icon\/24-en-wiki.png\" \/><\/a>",
        "audio": "<audio src=\"https:\/\/www.w3schools.com\/html\/horse.mp3\" class=\"audioplay en\"><\/audio>",
        "name_jp": null,
        "source_jp": "<a href=\"\" target=\"_blank\"><img width=\"24\" height=\"24\" src=\"\/images\/poster\/edupack\/icon\/24-jp-wiki.png\" \/><\/a>",
        "audio_jp": "<audio src=\"https:\/\/www.w3schools.com\/html\/horse.mp3\" class=\"audioplay jp\"><\/audio>",
        "name_de": "Y",
        "source_de": "<a href=\"\" target=\"_blank\"><img width=\"24\" height=\"24\" src=\"\/images\/poster\/edupack\/icon\/24-en-wiki.png\" \/><\/a>",
        "audio_de": "<audio src=\"https:\/\/www.w3schools.com\/html\/horse.mp3\" class=\"audioplay jp\"><\/audio>",
        "id": 55
    },
    {
        "name": "Z",
        "source": "<a href=\"\" target=\"_blank\"><img width=\"24\" height=\"24\" src=\"\/images\/poster\/edupack\/icon\/24-en-wiki.png\" \/><\/a>",
        "audio": "<audio src=\"https:\/\/www.w3schools.com\/html\/horse.mp3\" class=\"audioplay en\"><\/audio>",
        "name_jp": null,
        "source_jp": "<a href=\"\" target=\"_blank\"><img width=\"24\" height=\"24\" src=\"\/images\/poster\/edupack\/icon\/24-jp-wiki.png\" \/><\/a>",
        "audio_jp": "<audio src=\"https:\/\/www.w3schools.com\/html\/horse.mp3\" class=\"audioplay jp\"><\/audio>",
        "name_de": "Z",
        "source_de": "<a href=\"\" target=\"_blank\"><img width=\"24\" height=\"24\" src=\"\/images\/poster\/edupack\/icon\/24-en-wiki.png\" \/><\/a>",
        "audio_de": "<audio src=\"https:\/\/www.w3schools.com\/html\/horse.mp3\" class=\"audioplay jp\"><\/audio>",
        "id": 56
    },
    {
        "name": null,
        "source": "<a href=\"\" target=\"_blank\"><img width=\"24\" height=\"24\" src=\"\/images\/poster\/edupack\/icon\/24-en-wiki.png\" \/><\/a>",
        "audio": "<audio src=\"https:\/\/www.w3schools.com\/html\/horse.mp3\" class=\"audioplay en\"><\/audio>",
        "name_jp": null,
        "source_jp": "<a href=\"\" target=\"_blank\"><img width=\"24\" height=\"24\" src=\"\/images\/poster\/edupack\/icon\/24-jp-wiki.png\" \/><\/a>",
        "audio_jp": "<audio src=\"https:\/\/www.w3schools.com\/html\/horse.mp3\" class=\"audioplay jp\"><\/audio>",
        "name_de": "\u00e4",
        "source_de": "<a href=\"\" target=\"_blank\"><img width=\"24\" height=\"24\" src=\"\/images\/poster\/edupack\/icon\/24-en-wiki.png\" \/><\/a>",
        "audio_de": "<audio src=\"https:\/\/www.w3schools.com\/html\/horse.mp3\" class=\"audioplay jp\"><\/audio>",
        "id": 57
    },
    {
        "name": null,
        "source": "<a href=\"\" target=\"_blank\"><img width=\"24\" height=\"24\" src=\"\/images\/poster\/edupack\/icon\/24-en-wiki.png\" \/><\/a>",
        "audio": "<audio src=\"https:\/\/www.w3schools.com\/html\/horse.mp3\" class=\"audioplay en\"><\/audio>",
        "name_jp": null,
        "source_jp": "<a href=\"\" target=\"_blank\"><img width=\"24\" height=\"24\" src=\"\/images\/poster\/edupack\/icon\/24-jp-wiki.png\" \/><\/a>",
        "audio_jp": "<audio src=\"https:\/\/www.w3schools.com\/html\/horse.mp3\" class=\"audioplay jp\"><\/audio>",
        "name_de": "\u00f6",
        "source_de": "<a href=\"\" target=\"_blank\"><img width=\"24\" height=\"24\" src=\"\/images\/poster\/edupack\/icon\/24-en-wiki.png\" \/><\/a>",
        "audio_de": "<audio src=\"https:\/\/www.w3schools.com\/html\/horse.mp3\" class=\"audioplay jp\"><\/audio>",
        "id": 58
    },
    {
        "name": null,
        "source": "<a href=\"\" target=\"_blank\"><img width=\"24\" height=\"24\" src=\"\/images\/poster\/edupack\/icon\/24-en-wiki.png\" \/><\/a>",
        "audio": "<audio src=\"https:\/\/www.w3schools.com\/html\/horse.mp3\" class=\"audioplay en\"><\/audio>",
        "name_jp": null,
        "source_jp": "<a href=\"\" target=\"_blank\"><img width=\"24\" height=\"24\" src=\"\/images\/poster\/edupack\/icon\/24-jp-wiki.png\" \/><\/a>",
        "audio_jp": "<audio src=\"https:\/\/www.w3schools.com\/html\/horse.mp3\" class=\"audioplay jp\"><\/audio>",
        "name_de": "\u00fc",
        "source_de": "<a href=\"\" target=\"_blank\"><img width=\"24\" height=\"24\" src=\"\/images\/poster\/edupack\/icon\/24-en-wiki.png\" \/><\/a>",
        "audio_de": "<audio src=\"https:\/\/www.w3schools.com\/html\/horse.mp3\" class=\"audioplay jp\"><\/audio>",
        "id": 59
    },
    {
        "name": null,
        "source": "<a href=\"\" target=\"_blank\"><img width=\"24\" height=\"24\" src=\"\/images\/poster\/edupack\/icon\/24-en-wiki.png\" \/><\/a>",
        "audio": "<audio src=\"https:\/\/www.w3schools.com\/html\/horse.mp3\" class=\"audioplay en\"><\/audio>",
        "name_jp": null,
        "source_jp": "<a href=\"\" target=\"_blank\"><img width=\"24\" height=\"24\" src=\"\/images\/poster\/edupack\/icon\/24-jp-wiki.png\" \/><\/a>",
        "audio_jp": "<audio src=\"https:\/\/www.w3schools.com\/html\/horse.mp3\" class=\"audioplay jp\"><\/audio>",
        "name_de": "\u00df",
        "source_de": "<a href=\"\" target=\"_blank\"><img width=\"24\" height=\"24\" src=\"\/images\/poster\/edupack\/icon\/24-en-wiki.png\" \/><\/a>",
        "audio_de": "<audio src=\"https:\/\/www.w3schools.com\/html\/horse.mp3\" class=\"audioplay jp\"><\/audio>",
        "id": 60
    }
]